aioq3rcon/__init__.py
aioq3rcon/cli.py
aioq3rcon/client.py
aioq3rcon/errors.py
aio_q3_rcon-1.0.0.dist-info/entry_points.txt
aio_q3_rcon-1.0.0.dist-info/LICENSE
aio_q3_rcon-1.0.0.dist-info/WHEEL
aio_q3_rcon-1.0.0.dist-info/METADATA
aio_q3_rcon-1.0.0.dist-info/RECORD
