Metadata-Version: 2.1
Name: aio-q3-rcon
Version: 1.0.0
Summary: An async Quake 3 RCON implementation with a CLI
Home-page: https://github.com/Iapetus-11/aio-q3-rcon
License: MIT
Keywords: quake3rcon,quake3,rcon,q3,q3rcon,async,asyncio
Author: Milo Weinberg
Author-email: iapetus011@gmail.com
Requires-Python: >=3.10,<4.0
Classifier: License :: OSI Approved :: MIT License
Classifier: Programming Language :: Python :: 3
Classifier: Programming Language :: Python :: 3.10
Requires-Dist: asyncio-dgram (>=2.1.2,<3.0.0)
Project-URL: Repository, https://github.com/Iapetus-11/aio-q3-rcon
